jose5/__init__.py
jose5/__main__.py
jose5/command_line.py
jose5/processor.py
jose5-0.4.0.dist-info/METADATA
jose5-0.4.0.dist-info/WHEEL
jose5-0.4.0.dist-info/entry_points.txt
jose5-0.4.0.dist-info/top_level.txt
jose5-0.4.0.dist-info/RECORD
