Metadata-Version: 2.1
Name: jose5
Version: 0.4.0
Summary: JSON Composer
Home-page: https://github.com/aplazame/jose5
Author: Aplazame
Author-email: dev@aplazame.com
License: UNKNOWN
Platform: UNKNOWN
Classifier: Programming Language :: Python :: 3
Classifier: License :: OSI Approved :: MIT License
Classifier: Operating System :: OS Independent
Requires-Python: >=3.6
